llama_index/readers/web/__init__.py
llama_index/readers/web/async_web/README.md
llama_index/readers/web/async_web/__init__.py
llama_index/readers/web/async_web/base.py
llama_index/readers/web/beautiful_soup_web/README.md
llama_index/readers/web/beautiful_soup_web/__init__.py
llama_index/readers/web/beautiful_soup_web/base.py
llama_index/readers/web/beautiful_soup_web/requirements.txt
llama_index/readers/web/knowledge_base/README.md
llama_index/readers/web/knowledge_base/__init__.py
llama_index/readers/web/knowledge_base/base.py
llama_index/readers/web/knowledge_base/requirements.txt
llama_index/readers/web/main_content_extractor/README.md
llama_index/readers/web/main_content_extractor/__init__.py
llama_index/readers/web/main_content_extractor/base.py
llama_index/readers/web/main_content_extractor/requirements.txt
llama_index/readers/web/news/README.md
llama_index/readers/web/news/__init__.py
llama_index/readers/web/news/base.py
llama_index/readers/web/news/requirements.txt
llama_index/readers/web/readability_web/README.md
llama_index/readers/web/readability_web/Readability.js
llama_index/readers/web/readability_web/__init__.py
llama_index/readers/web/readability_web/base.py
llama_index/readers/web/readability_web/requirements.txt
llama_index/readers/web/rss/README.md
llama_index/readers/web/rss/__init__.py
llama_index/readers/web/rss/base.py
llama_index/readers/web/rss_news/README.md
llama_index/readers/web/rss_news/__init__.py
llama_index/readers/web/rss_news/base.py
llama_index/readers/web/rss_news/sample_rss_feeds.opml
llama_index/readers/web/simple_web/README.md
llama_index/readers/web/simple_web/__init__.py
llama_index/readers/web/simple_web/base.py
llama_index/readers/web/simple_web/requirements.txt
llama_index/readers/web/sitemap/README.md
llama_index/readers/web/sitemap/__init__.py
llama_index/readers/web/sitemap/base.py
llama_index/readers/web/sitemap/requirements.txt
llama_index/readers/web/trafilatura_web/README.md
flying_delta_readers_web-0.1.0.dist-info/METADATA
flying_delta_readers_web-0.1.0.dist-info/WHEEL
flying_delta_readers_web-0.1.0.dist-info/RECORD
